{
 "cells": [
  {
   "cell_type": "code",
   "execution_count": 1,
   "metadata": {},
   "outputs": [],
   "source": [
    "def func_range():\n",
    "    return sum(range(2,101,2))\n",
    "\n",
    "def func_generator():\n",
    "    return sum(i*2 for i in range(51)) \n",
    "\n",
    "def func_list():\n",
    "    return sum([i*2 for i in range(51)]) "
   ]
  },
  {
   "cell_type": "code",
   "execution_count": 2,
   "metadata": {},
   "outputs": [
    {
     "name": "stdout",
     "output_type": "stream",
     "text": [
      "CPU times: user 4 µs, sys: 0 ns, total: 4 µs\n",
      "Wall time: 5.72 µs\n"
     ]
    },
    {
     "data": {
      "text/plain": [
       "2550"
      ]
     },
     "execution_count": 2,
     "metadata": {},
     "output_type": "execute_result"
    }
   ],
   "source": [
    "%%time\n",
    "func_range()"
   ]
  },
  {
   "cell_type": "code",
   "execution_count": 3,
   "metadata": {},
   "outputs": [
    {
     "name": "stdout",
     "output_type": "stream",
     "text": [
      "CPU times: user 13 µs, sys: 1 µs, total: 14 µs\n",
      "Wall time: 16.2 µs\n"
     ]
    },
    {
     "data": {
      "text/plain": [
       "2550"
      ]
     },
     "execution_count": 3,
     "metadata": {},
     "output_type": "execute_result"
    }
   ],
   "source": [
    "%%time\n",
    "func_generator()"
   ]
  },
  {
   "cell_type": "code",
   "execution_count": 4,
   "metadata": {},
   "outputs": [
    {
     "name": "stdout",
     "output_type": "stream",
     "text": [
      "CPU times: user 12 µs, sys: 1 µs, total: 13 µs\n",
      "Wall time: 16 µs\n"
     ]
    },
    {
     "data": {
      "text/plain": [
       "2550"
      ]
     },
     "execution_count": 4,
     "metadata": {},
     "output_type": "execute_result"
    }
   ],
   "source": [
    "%%time\n",
    "func_list()"
   ]
  },
  {
   "cell_type": "code",
   "execution_count": 5,
   "metadata": {},
   "outputs": [
    {
     "name": "stdout",
     "output_type": "stream",
     "text": [
      "  2           0 LOAD_GLOBAL              0 (sum)\n",
      "              2 LOAD_GLOBAL              1 (range)\n",
      "              4 LOAD_CONST               1 (2)\n",
      "              6 LOAD_CONST               2 (101)\n",
      "              8 LOAD_CONST               1 (2)\n",
      "             10 CALL_FUNCTION            3\n",
      "             12 CALL_FUNCTION            1\n",
      "             14 RETURN_VALUE\n"
     ]
    }
   ],
   "source": [
    "import dis\n",
    "dis.dis(func_range)"
   ]
  },
  {
   "cell_type": "code",
   "execution_count": 6,
   "metadata": {},
   "outputs": [
    {
     "name": "stdout",
     "output_type": "stream",
     "text": [
      "  5           0 LOAD_GLOBAL              0 (sum)\n",
      "              2 LOAD_CONST               1 (<code object <genexpr> at 0x1062df0c0, file \"<ipython-input-1-7f72d8eb738e>\", line 5>)\n",
      "              4 LOAD_CONST               2 ('func_generator.<locals>.<genexpr>')\n",
      "              6 MAKE_FUNCTION            0\n",
      "              8 LOAD_GLOBAL              1 (range)\n",
      "             10 LOAD_CONST               3 (51)\n",
      "             12 CALL_FUNCTION            1\n",
      "             14 GET_ITER\n",
      "             16 CALL_FUNCTION            1\n",
      "             18 CALL_FUNCTION            1\n",
      "             20 RETURN_VALUE\n"
     ]
    }
   ],
   "source": [
    "dis.dis(func_generator)"
   ]
  },
  {
   "cell_type": "code",
   "execution_count": 7,
   "metadata": {},
   "outputs": [
    {
     "name": "stdout",
     "output_type": "stream",
     "text": [
      "  8           0 LOAD_GLOBAL              0 (sum)\n",
      "              2 LOAD_CONST               1 (<code object <listcomp> at 0x1062df420, file \"<ipython-input-1-7f72d8eb738e>\", line 8>)\n",
      "              4 LOAD_CONST               2 ('func_list.<locals>.<listcomp>')\n",
      "              6 MAKE_FUNCTION            0\n",
      "              8 LOAD_GLOBAL              1 (range)\n",
      "             10 LOAD_CONST               3 (51)\n",
      "             12 CALL_FUNCTION            1\n",
      "             14 GET_ITER\n",
      "             16 CALL_FUNCTION            1\n",
      "             18 CALL_FUNCTION            1\n",
      "             20 RETURN_VALUE\n"
     ]
    }
   ],
   "source": [
    "dis.dis(func_list)"
   ]
  },
  {
   "cell_type": "code",
   "execution_count": null,
   "metadata": {},
   "outputs": [],
   "source": []
  }
 ],
 "metadata": {
  "kernelspec": {
   "display_name": "Python 3",
   "language": "python",
   "name": "python3"
  },
  "language_info": {
   "codemirror_mode": {
    "name": "ipython",
    "version": 3
   },
   "file_extension": ".py",
   "mimetype": "text/x-python",
   "name": "python",
   "nbconvert_exporter": "python",
   "pygments_lexer": "ipython3",
   "version": "3.6.6"
  }
 },
 "nbformat": 4,
 "nbformat_minor": 2
}
